Workbook

Sheet Executive Analytics & KPIs
B1: TVS Certified - Conversion Analytics & Performance Intelligence
B2: January to September 2026 Executive Summary & Regional Conversion Metrics (4,314 Units)
B4: TOTAL CONVERTED | D4: AUCTION TURNOVER | F4: TVS INCOME (EX-GST) | H4: TVS INCOME (INCL-GST) | J4: AVG TVS MARGIN %
B5: =COUNTA('Conversion Analytics (Master)'!D4:D4317) | D5: =SUM('Conversion Analytics (Master)'!I4:I4317) | F5: =SUM('Conversion Analytics (Master)'!M4:M4317) | H5: =SUM('Conversion Analytics (Master)'!N4:N4317) | J5: =AVERAGE('Conversion Analytics (Master)'!O4:O4317)
B8: REGIONAL PERFORMANCE BREAKDOWN
B9: State | C9: Units Converted | D9: GMV (Turnover) | E9: TVS Income (Ex GST) | F9: TVS Income (Inc GST) | G9: Avg Bid Value | H9: Avg Take Rate %
B10: AP/TS | C10: =COUNTIF('Conversion Analytics (Master)'!$C$4:$C$4317, B10) | D10: =SUMIF('Conversion Analytics (Master)'!$C$4:$C$4317, B10, 'Conversion Analytics (Master)'!$I$4:$I$4317) | E10: =SUMIF('Conversion Analytics (Master)'!$C$4:$C$4317, B10, 'Conversion Analytics (Master)'!$M$4:$M$4317) | F10: =SUMIF('Conversion Analytics (Master)'!$C$4:$C$4317, B10, 'Conversion Analytics (Master)'!$N$4:$N$4317) | G10: =IF(C10>0, D10/C10, 0) | H10: =IF(D10>0, E10/D10, 0)
B11: Kerala | C11: =COUNTIF('Conversion Analytics (Master)'!$C$4:$C$4317, B11) | D11: =SUMIF('Conversion Analytics (Master)'!$C$4:$C$4317, B11, 'Conversion Analytics (Master)'!$I$4:$I$4317) | E11: =SUMIF('Conversion Analytics (Master)'!$C$4:$C$4317, B11, 'Conversion Analytics (Master)'!$M$4:$M$4317) | F11: =SUMIF('Conversion Analytics (Master)'!$C$4:$C$4317, B11, 'Conversion Analytics (Master)'!$N$4:$N$4317) | G11: =IF(C11>0, D11/C11, 0) | H11: =IF(D11>0, E11/D11, 0)
B12: TN | C12: =COUNTIF('Conversion Analytics (Master)'!$C$4:$C$4317, B12) | D12: =SUMIF('Conversion Analytics (Master)'!$C$4:$C$4317, B12, 'Conversion Analytics (Master)'!$I$4:$I$4317) | E12: =SUMIF('Conversion Analytics (Master)'!$C$4:$C$4317, B12, 'Conversion Analytics (Master)'!$M$4:$M$4317) | F12: =SUMIF('Conversion Analytics (Master)'!$C$4:$C$4317, B12, 'Conversion Analytics (Master)'!$N$4:$N$4317) | G12: =IF(C12>0, D12/C12, 0) | H12: =IF(D12>0, E12/D12, 0)
B13: TOTAL | C13: =SUM(C10:C12) | D13: =SUM(D10:D12) | E13: =SUM(E10:E12) | F13: =SUM(F10:F12) | G13: =IF(C13>0, D13/C13, 0) | H13: =IF(D13>0, E13/D13, 0)

Sheet Conversion Analytics (Master)
A1: TVS Certified - Conversion Analytics Master Dataset
A2: January to September 2026 Analytical Inventory Profile (4,314 Converted Units)
A3: FY | B3: Month | C3: State | D3: Vehicle Number | E3: Make | F3: Model | G3: Year | H3: Odometer | I3: Final Bid Value | J3: Seller Name | K3: Seller Segment | L3: Buyer Name | M3: Total Income (ex. GST) | N3: Total Income | O3: TVS Margin %
A4: FY26 | B4: Jan | C4: AP/TS | D4: AP31AS1112 | E4: HYUNDAI | F4: Getz | G4: 2007 | H4: 77543 | I4: 55000 | J4: Exchange VIZAG | K4: Captive | L4: Gadi Sri Bharathi | M4: 4237.29 | N4: 5000 | O4: =IF(AND(ISNUMBER(M4), ISNUMBER(I4), I4>0), M4/I4, "")
A5: FY26 | B5: Jan | C5: AP/TS | D5: AP31CS7594 | E5: HONDA | F5: Mobilio | G5: 2014 | H5: 98056 | I5: 265000 | J5: Exchange VIZAG | K5: Captive | L5: Siva Reddy Gudla | M5: 12711.86 | N5: 15000 | O5: =IF(AND(ISNUMBER(M5), ISNUMBER(I5), I5>0), M5/I5, "")
A6: FY26 | B6: Jan | C6: AP/TS | D6: TS09EY7211 | E6: NISSAN | F6: Micra | G6: 2017 | H6: 113473 | I6: 190000 | J6: Exchange HYDERABAD | K6: Captive | L6: Viswanadhapalli Aravind | M6: 8474.58 | N6: 10000 | O6: =IF(AND(ISNUMBER(M6), ISNUMBER(I6), I6>0), M6/I6, "")
A7: FY26 | B7: Jan | C7: AP/TS | D7: AP31CE7777 | E7: RENAULT | F7: Scala | G7: 2012 | H7: 255641 | I7: 97000 | J7: Exchange VIZAG | K7: Captive | L7: Kaki Dinesh Kumar | M7: 5932.2 | N7: 7000 | O7: =IF(AND(ISNUMBER(M7), ISNUMBER(I7), I7>0), M7/I7, "")
A8: FY26 | B8: Jan | C8: AP/TS | D8: AP31DF2198 | E8: HONDA | F8: Jazz | G8: 2016 | H8: 41567 | I8: 327500 | J8: Exchange VIZAG | K8: Captive | L8: Chukka Satish | M8: 10593.22 | N8: 12500 | O8: =IF(AND(ISNUMBER(M8), ISNUMBER(I8), I8>0), M8/I8, "")
A9: FY26 | B9: Jan | C9: AP/TS | D9: AP31BM4257 | E9: CHEVROLET | F9: Spark | G9: 2015 | H9: 141008 | I9: 50000 | J9: Kesireddi Saikiran | K9: Non-Captive | L9: Siva Reddy Gudla | M9: 4237.29 | N9: 5000 | O9: =IF(AND(ISNUMBER(M9), ISNUMBER(I9), I9>0), M9/I9, "")
A10: FY26 | B10: Jan | C10: AP/TS | D10: TS08GV4028 | E10: HONDA | F10: Amaze | G10: 2019 | H10: 74555 | I10: 380000 | J10: Exchange HYDERABAD | K10: Captive | L10: Ganothula Brahma Reddy | M10: 8474.58 | N10: 10000 | O10: =IF(AND(ISNUMBER(M10), ISNUMBER(I10), I10>0), M10/I10, "")
A11: FY26 | B11: Jan | C11: AP/TS | D11: TS09EB2697 | E11: HONDA | F11: City | G11: 2014 | H11: 158986 | I11: 265000 | J11: Exchange HYDERABAD | K11: Captive | L11: Uppari Sandeep Kumar | M11: 8474.58 | N11: 10000 | O11: =IF(AND(ISNUMBER(M11), ISNUMBER(I11), I11>0), M11/I11, "")
A12: FY26 | B12: Jan | C12: AP/TS | D12: TS11EC4656 | E12: HONDA | F12: Amaze | G12: 2015 | H12: 178445 | I12: 215000 | J12: Exchange HYDERABAD | K12: Captive | L12: Puneet Gupta | M12: 8474.58 | N12: 10000 | O12: =IF(AND(ISNUMBER(M12), ISNUMBER(I12), I12>0), M12/I12, "")
A13: FY26 | B13: Jan | C13: AP/TS | D13: AP39JV0286 | E13: TATA | F13: Tiago | G13: 2021 | H13: 58833 | I13: 335000 | J13: Exchange VIJAYAWADA | K13: Captive | L13: Naga Suresh Polukonda | M13: 8474.58 | N13: 10000 | O13: =IF(AND(ISNUMBER(M13), ISNUMBER(I13), I13>0), M13/I13, "")
A14: FY26 | B14: Jan | C14: AP/TS | D14: AP31DD1661 | E14: HONDA | F14: Jazz | G14: 2015 | H14: 132923 | I14: 240000 | J14: Exchange VIZAG | K14: Captive | L14: Raju Avaala | M14: 8474.58 | N14: 10000 | O14: =IF(AND(ISNUMBER(M14), ISNUMBER(I14), I14>0), M14/I14, "")
A15: FY26 | B15: Jan | C15: AP/TS | D15: AP31EP0888 | E15: HONDA | F15: Amaze | G15: 2018 | H15: 85923 | I15: 400000 | J15: Exchange VIZAG | K15: Captive | L15: Kaki Dinesh Kumar | M15: 12711.86 | N15: 15000 | O15: =IF(AND(ISNUMBER(M15), ISNUMBER(I15), I15>0), M15/I15, "")
... A318: FY26 | B318: Jan | C318: TN | D318: TN06B2738 | E318: HYUNDAI | F318: I10 | G318: 2010 | H318: 124567 | I318: 180000 | J318: Nirmal | K318: Non-Captive | L318: Ragupathy Cars | M318: 4237.29 | N318: 5000 | O318: =IF(AND(ISNUMBER(M318), ISNUMBER(I318), I318>0), M318/I318, "")
A319: FY26 | B319: Jan | C319: TN | D319: KL24L2932 | E319: HONDA | F319: Jazz | I319: 350000 | J319: Nippon Motor Corporation Pvt Ltd | K319: Non-Captive | L319: Shamnad AH | M319: 5932.2 | N319: 7000 | O319: =IF(AND(ISNUMBER(M319), ISNUMBER(I319), I319>0), M319/I319, "")
A320: FY26 | B320: Jan | C320: TN | D320: KL29M9531 | E320: HYUNDAI | F320: Verna | I320: 360000 | J320: Nippon Motor Corporation Pvt Ltd | K320: Non-Captive | L320: Shamnad AH | M320: 5932.2 | N320: 7000 | O320: =IF(AND(ISNUMBER(M320), ISNUMBER(I320), I320>0), M320/I320, "")
A321: FY26 | B321: Jan | C321: TN | D321: TN13H5670 | E321: TATA | F321: Tiago | G321: 2017 | H321: 79008 | I321: 250000 | J321: Lakshmi Tata | K321: Non-Captive | L321: Omega Car Zone | M321: 4237.29 | N321: 5000 | O321: =IF(AND(ISNUMBER(M321), ISNUMBER(I321), I321>0), M321/I321, "")
A322: FY26 | B322: Jan | C322: TN | D322: TN10BB1885 | E322: MARUTI SUZUKI | F322: Swift Dzire | G322: 2017 | H322: 110113 | I322: 400000 | J322: Lakshmi Tata | K322: Non-Captive | L322: Thiya Cars | M322: 4237.29 | N322: 5000 | O322: =IF(AND(ISNUMBER(M322), ISNUMBER(I322), I322>0), M322/I322, "")
A323: FY26 | B323: Jan | C323: TN | D323: TN12AM7659 | E323: RENAULT | F323: Kiger | G323: 2021 | H323: 41621 | I323: 260000 | J323: Lakshmi Tata | K323: Non-Captive | L323: Thiya Cars | M323: 4237.29 | N323: 5000 | O323: =IF(AND(ISNUMBER(M323), ISNUMBER(I323), I323>0), M323/I323, "")
A324: FY26 | B324: Jan | C324: TN | D324: TN02BC1360 | E324: RENAULT | F324: Logdy | G324: 2015 | H324: 67756 | I324: 300000 | J324: Lakshmi Tata | K324: Non-Captive | L324: Thiya Cars | M324: 4237.29 | N324: 5000 | O324: =IF(AND(ISNUMBER(M324), ISNUMBER(I324), I324>0), M324/I324, "")
A325: FY26 | B325: Jan | C325: TN | D325: TN13E0081 | E325: MARUTI SUZUKI | F325: Alto | G325: 2016 | H325: 44733 | I325: 150000 | J325: Lakshmi Tata | K325: Non-Captive | L325: Thiya Cars | M325: 4237.29 | N325: 5000 | O325: =IF(AND(ISNUMBER(M325), ISNUMBER(I325), I325>0), M325/I325, "")
A326: FY26 | B326: Jan | C326: TN | D326: TN12E7768 | E326: HYUNDAI | F326: Grand I10 | G326: 2014 | H326: 77642 | I326: 200000 | J326: Lakshmi Tata | K326: Non-Captive | L326: Thiya Cars | M326: 4237.29 | N326: 5000 | O326: =IF(AND(ISNUMBER(M326), ISNUMBER(I326), I326>0), M326/I326, "")
A327: FY26 | B327: Jan | C327: TN | D327: TN01U6000 | E327: MARUTI SUZUKI | F327: Alto | G327: 1998 | H327: 73444 | I327: 25000 | J327: Lakshmi Tata | K327: Non-Captive | L327: Thiya Cars | M327: 4237.29 | N327: 5000 | O327: =IF(AND(ISNUMBER(M327), ISNUMBER(I327), I327>0), M327/I327, "")
A328: FY26 | B328: Jan | C328: TN | D328: TN22CD7366 | E328: MARUTI SUZUKI | F328: Swift | G328: 2012 | H328: 55256 | I328: 160000 | J328: Lakshmi Tata | K328: Non-Captive | L328: Thiya Cars | M328: 4237.29 | N328: 5000 | O328: =IF(AND(ISNUMBER(M328), ISNUMBER(I328), I328>0), M328/I328, "")
A329: FY26 | B329: Jan | C329: TN | D329: TN07AL9019 | E329: HONDA | F329: City | G329: 2007 | H329: 94292 | I329: 100000 | J329: Lakshmi Tata | K329: Non-Captive | L329: Thiya Cars | M329: 4237.29 | N329: 5000 | O329: =IF(AND(ISNUMBER(M329), ISNUMBER(I329), I329>0), M329/I329, "")
A330: FY26 | B330: Jan | C330: TN | D330: TN18P1035 | E330: VOLKSWAGEN | F330: Polo | G330: 2012 | H330: 131005 | I330: 200000 | J330: Lakshmi Tata | K330: Non-Captive | L330: Thiya Cars | M330: 4237.29 | N330: 5000 | O330: =IF(AND(ISNUMBER(M330), ISNUMBER(I330), I330>0), M330/I330, "")
A331: FY26 | B331: Jan | C331: TN | D331: TN14W0344 | E331: TATA | F331: Tiago | G331: 2019 | H331: 72435 | I331: 270000 | J331: Lakshmi Tata | K331: Non-Captive | L331: Thiya Cars | M331: 4237.29 | N331: 5000 | O331: =IF(AND(ISNUMBER(M331), ISNUMBER(I331), I331>0), M331/I331, "")
A332: FY26 | B332: Jan | C332: TN | D332: TN03AB1023 | E332: TATA | F332: Tiago | G332: 2019 | H332: 116457 | I332: 260000 | J332: Lakshmi Tata | K332: Non-Captive | L332: Thiya Cars | M332: 4237.29 | N332: 5000 | O332: =IF(AND(ISNUMBER(M332), ISNUMBER(I332), I332>0), M332/I332, "")
... A334: FY26 | B334: Jan | C334: TN | D334: TN09BM0228 | E334: MARUTI SUZUKI | F334: Swift | G334: 2011 | H334: 174000 | I334: 185000 | J334: Khivraj Motor | K334: Non-Captive | L334: Balakrishnan | M334: 5084.75 | N334: 6000 | O334: =IF(AND(ISNUMBER(M334), ISNUMBER(I334), I334>0), M334/I334, "")
A335: FY26 | B335: Jan | C335: TN | D335: TN30BL266 | E335: MARUTI SUZUKI | F335: S-Cross | I335: 485000 | J335: Khivraj Motor | K335: Non-Captive | L335: Balakrishnan | M335: 5084.75 | N335: 6000 | O335: =IF(AND(ISNUMBER(M335), ISNUMBER(I335), I335>0), M335/I335, "")
A336: FY26 | B336: Jan | C336: TN | D336: TN09BA4646 | E336: MARUTI SUZUKI | F336: Zen | G336: 2009 | H336: 82508 | I336: 90000 | J336: Khivraj Motor | K336: Non-Captive | L336: AAA Cars | M336: 5084.75 | N336: 6000 | O336: =IF(AND(ISNUMBER(M336), ISNUMBER(I336), I336>0), M336/I336, "")
A337: FY26 | B337: Jan | C337: TN | D337: TN01BB5113 | E337: HYUNDAI | F337: Creta | G337: 2016 | H337: 67577 | I337: 465000 | J337: Khivraj Motor | K337: Non-Captive | L337: Aasim Motor | M337: 5084.75 | N337: 6000 | O337: =IF(AND(ISNUMBER(M337), ISNUMBER(I337), I337>0), M337/I337, "")
A338: FY26 | B338: Jan | C338: TN | D338: TN01AQ1698 | E338: MARUTI SUZUKI | F338: Swift Dzire | G338: 2011 | H338: 65103 | I338: 173000 | J338: Khivraj Motor | K338: Non-Captive | L338: Surendhar Cars | M338: 5084.75 | N338: 6000 | O338: =IF(AND(ISNUMBER(M338), ISNUMBER(I338), I338>0), M338/I338, "")
A339: FY26 | B339: Jan | C339: TN | D339: TN09CT3233 | E339: HYUNDAI | F339: Creta | G339: 2019 | H339: 44563 | I339: 530000 | J339: Harsha | K339: Non-Captive | L339: Pine Autos | M339: 5508.47 | N339: 6500 | O339: =IF(AND(ISNUMBER(M339), ISNUMBER(I339), I339>0), M339/I339, "")
A340: FY26 | B340: Jan | C340: TN | D340: KL04AG5541 | E340: MARUTI SUZUKI | F340: Ritz | I340: 210000 | J340: Nippon Motor Corporation Pvt Ltd | K340: Non-Captive | L340: Shamnad AH | M340: 5932.2 | N340: 7000 | O340: =IF(AND(ISNUMBER(M340), ISNUMBER(I340), I340>0), M340/I340, "")
A341: FY26 | B341: Jan | C341: TN | D341: TN01BP4170 | E341: HYUNDAI | F341: Aura | G341: 2022 | H341: 1974 | I341: 620000 | J341: Avis India | K341: Non-Captive | L341: Nirmal Cars | M341: 12711.86 | N341: 15000 | O341: =IF(AND(ISNUMBER(M341), ISNUMBER(I341), I341>0), M341/I341, "")
A342: FY26 | B342: Jan | C342: TN | D342: TN38CB0766 | E342: HONDA | F342: Amaze | G342: 2015 | H342: 65500 | I342: 190000 | J342: Sai Cars CBE | K342: Non-Captive | L342: KSM AUTO CONSULTING | M342: 4237.29 | N342: 5000 | O342: =IF(AND(ISNUMBER(M342), ISNUMBER(I342), I342>0), M342/I342, "")
A343: FY26 | B343: Jan | C343: TN | D343: TN01AC1548 | E343: TATA | F343: Indica | G343: 2006 | H343: 160671 | I343: 60000 | J343: Sai Cars CBE | K343: Non-Captive | L343: KSM AUTO CONSULTING | M343: 4237.29 | N343: 5000 | O343: =IF(AND(ISNUMBER(M343), ISNUMBER(I343), I343>0), M343/I343, "")
A344: FY26 | B344: Jan | C344: TN | D344: TN05AS2905 | E344: TOYOTA | F344: Etios | G344: 2013 | H344: 83523 | I344: 180000 | J344: Sai Cars CBE | K344: Non-Captive | L344: YUGA DHEERAN CARS | M344: 4237.29 | N344: 5000 | O344: =IF(AND(ISNUMBER(M344), ISNUMBER(I344), I344>0), M344/I344, "")
A345: FY26 | B345: Jan | C345: TN | D345: TN38BZ6252 | E345: MARUTI SUZUKI | F345: Alto K10 | G345: 2014 | H345: 102682 | I345: 170000 | J345: EXCHANGE ROTN | K345: Captive | L345: UZHAVAN ENTERPRISE | M345: 4237.29 | N345: 5000 | O345: =IF(AND(ISNUMBER(M345), ISNUMBER(I345), I345>0), M345/I345, "")
A346: FY26 | B346: Jan | C346: TN | D346: TN07BU5814 | E346: MARUTI SUZUKI | F346: Wagon R | G346: 2013 | H346: 22988 | I346: 205000 | J346: Sai Cars CBE | K346: Non-Captive | L346: SIVASHANKAR CARS | M346: 4237.29 | N346: 5000 | O346: =IF(AND(ISNUMBER(M346), ISNUMBER(I346), I346>0), M346/I346, "")
A347: FY26 | B347: Jan | C347: TN | D347: TN38CT0789 | E347: MARUTI SUZUKI | F347: Celerio | G347: 2019 | H347: 46670 | I347: 210000 | J347: EXCHANGE ROTN | K347: Captive | L347: 9 MILES CARZ | M347: 4237.29 | N347: 5000 | O347: =IF(AND(ISNUMBER(M347), ISNUMBER(I347), I347>0), M347/I347, "")
A348: FY26 | B348: Jan | C348: TN | D348: KA53MA6163 | E348: HYUNDAI | F348: I10 | G348: 2013 | H348: 130298 | I348: 150000 | J348: DINDIGUL VALUE CAR | K348: Non-Captive | L348: 9 MILES CARZ | M348: 4237.29 | N348: 5000 | O348: =IF(AND(ISNUMBER(M348), ISNUMBER(I348), I348>0), M348/I348, "")
A349: FY26 | B349: Jan | C349: TN | D349: TN38CB2589 | E349: HYUNDAI | F349: Grand I10 | G349: 2015 | H349: 54895 | I349: 190000 | J349: Sai Cars CBE | K349: Non-Captive | L349: Dheera Cars | M349: 4237.29 | N349: 5000 | O349: =IF(AND(ISNUMBER(M349), ISNUMBER(I349), I349>0), M349/I349, "")
A350: FY26 | B350: Jan | C350: TN | D350: TN91W8213 | E350: MARUTI SUZUKI | F350: Alto | G350: 2018 | H350: 25663 | I350: 210000 | J350: Sai Cars CBE | K350: Non-Captive | L350: Dheera Cars | M350: 4237.29 | N350: 5000 | O350: =IF(AND(ISNUMBER(M350), ISNUMBER(I350), I350>0), M350/I350, "")
A351: FY26 | B351: Jan | C351: TN | D351: TN38BV1258 | E351: FORD | F351: Figo | G351: 2013 | H351: 11589 | I351: 130000 | J351: Sai Cars CBE | K351: Non-Captive | L351: Dheera Cars | M351: 4237.29 | N351: 5000 | O351: =IF(AND(ISNUMBER(M351), ISNUMBER(I351), I351>0), M351/I351, "")
A352: FY26 | B352: Jan | C352: TN | D352: TN09BK9082 | E352: HYUNDAI | F352: I10 | G352: 2011 | H352: 89684 | I352: 115000 | J352: Sai Cars CBE | K352: Non-Captive | L352: Dheera Cars | M352: 4237.29 | N352: 5000 | O352: =IF(AND(ISNUMBER(M352), ISNUMBER(I352), I352>0), M352/I352, "")
... A386: FY26 | B386: Jan | C386: TN | D386: TN06K7642 | E386: VOLKSWAGEN | F386: Polo | G386: 2013 | H386: 81914 | I386: 180000 | J386: Khivraj Motor | K386: Non-Captive | L386: Prem Cars | M386: 5084.75 | N386: 6000 | O386: =IF(AND(ISNUMBER(M386), ISNUMBER(I386), I386>0), M386/I386, "")
A387: FY26 | B387: Jan | C387: TN | D387: TN09CE6262 | E387: MARUTI SUZUKI | F387: Brezza | I387: 473000 | J387: Khivraj Motor | K387: Non-Captive | L387: Senthil Cars | M387: 5084.75 | N387: 6000 | O387: =IF(AND(ISNUMBER(M387), ISNUMBER(I387), I387>0), M387/I387, "")
A388: FY26 | B388: Jan | C388: TN | D388: TN30BQ9174 | E388: HONDA | F388: Amaze | G388: 2020 | H388: 36298 | I388: 485000 | J388: EXCHANGE ROTN | K388: Captive | L388: Sangeetha Enterprises | M388: 12711.86 | N388: 15000 | O388: =IF(AND(ISNUMBER(M388), ISNUMBER(I388), I388>0), M388/I388, "")
A389: FY26 | B389: Jan | C389: TN | D389: DL3CCE6673 | E389: HONDA | F389: Jazz | G389: 2016 | H389: 81658 | I389: 250000 | J389: EXCHANGE ROTN | K389: Captive | L389: MS Cars | M389: 5932.2 | N389: 7000 | O389: =IF(AND(ISNUMBER(M389), ISNUMBER(I389), I389>0), M389/I389, "")
A390: FY26 | B390: Jan | C390: TN | D390: TN72BA1515 | E390: HONDA | F390: City | G390: 2014 | H390: 143498 | I390: 375000 | J390: EXCHANGE ROTN | K390: Captive | L390: Value Cars | M390: 12711.86 | N390: 15000 | O390: =IF(AND(ISNUMBER(M390), ISNUMBER(I390), I390>0), M390/I390, "")
A391: FY26 | B391: Jan | C391: TN | D391: TN30CE5088 | E391: HONDA | F391: Amaze | G391: 2023 | H391: 118492 | I391: 435000 | J391: EXCHANGE ROTN | K391: Captive | L391: Vadivel Madesh | M391: 4237.29 | N391: 5000 | O391: =IF(AND(ISNUMBER(M391), ISNUMBER(I391), I391>0), M391/I391, "")
A392: FY26 | B392: Jan | C392: TN | D392: TN10H8377 | E392: MARUTI SUZUKI | F392: Zen | G392: 2004 | H392: 127346 | I392: 70000 | J392: EXCHANGE ROTN | K392: Captive | L392: Gugha Cars | M392: 4237.29 | N392: 5000 | O392: =IF(AND(ISNUMBER(M392), ISNUMBER(I392), I392>0), M392/I392, "")
A393: FY26 | B393: Jan | C393: TN | D393: TN59BH8394 | E393: MARUTI SUZUKI | F393: Ciaz | G393: 2015 | H393: 110535 | I393: 370000 | J393: EXCHANGE ROTN | K393: Captive | L393: Selva Motors | M393: 12711.86 | N393: 15000 | O393: =IF(AND(ISNUMBER(M393), ISNUMBER(I393), I393>0), M393/I393, "")
A394: FY26 | B394: Jan | C394: TN | D394: TN10AA7457 | E394: MARUTI SUZUKI | F394: Swift Dzire | G394: 2010 | H394: 209748 | I394: 170000 | J394: EXCHANGE CHENNAI | K394: Captive | L394: Nirmal Cars | M394: 4237.29 | N394: 5000 | O394: =IF(AND(ISNUMBER(M394), ISNUMBER(I394), I394>0), M394/I394, "")
A395: FY26 | B395: Jan | C395: TN | D395: TN06Y6543 | E395: HONDA | F395: Amaze | G395: 2019 | H395: 37168 | I395: 450000 | J395: EXCHANGE CHENNAI | K395: Captive | L395: Thiya Cars | M395: 4237.29 | N395: 5000 | O395: =IF(AND(ISNUMBER(M395), ISNUMBER(I395), I395>0), M395/I395, "")
A396: FY26 | B396: Jan | C396: TN | D396: TN49BA3864 | E396: HYUNDAI | F396: Grand I10 | G396: 2014 | H396: 79642 | I396: 250000 | J396: EXCHANGE ROTN | K396: Captive | L396: Sai cars | M396: 6779.66 | N396: 8000 | O396: =IF(AND(ISNUMBER(M396), ISNUMBER(I396), I396>0), M396/I396, "")
A397: FY26 | B397: Jan | C397: TN | D397: TN30BV6746 | E397: HYUNDAI | F397: Eon | G397: 2017 | H397: 28450 | I397: 240000 | J397: EXCHANGE ROTN | K397: Captive | L397: SMS Cars | M397: 12711.86 | N397: 15000 | O397: =IF(AND(ISNUMBER(M397), ISNUMBER(I397), I397>0), M397/I397, "")
A398: FY26 | B398: Jan | C398: TN | D398: TN33AT6482 | E398: MARUTI SUZUKI | F398: Alto | G398: 2011 | H398: 43110 | I398: 200000 | J398: EXCHANGE ROTN | K398: Captive | L398: YUGA DHEERAN CARS | M398: 8474.58 | N398: 10000 | O398: =IF(AND(ISNUMBER(M398), ISNUMBER(I398), I398>0), M398/I398, "")
A399: FY26 | B399: Jan | C399: TN | D399: TN19AK4891 | E399: MARUTI SUZUKI | F399: Swift | G399: 2018 | H399: 91489 | I399: 500000 | J399: EXCHANGE ROTN | K399: Captive | L399: Gugha Cars | M399: 8474.58 | N399: 10000 | O399: =IF(AND(ISNUMBER(M399), ISNUMBER(I399), I399>0), M399/I399, "")
... A402: FY26 | B402: Jan | C402: TN | D402: TN58AU4124 | E402: TATA | F402: Tiago | G402: 2017 | H402: 92823 | I402: 285000 | J402: EXCHANGE ROTN | K402: Captive | L402: Dheera Cars | M402: 12711.86 | N402: 15000 | O402: =IF(AND(ISNUMBER(M402), ISNUMBER(I402), I402>0), M402/I402, "")
A403: FY26 | B403: Jan | C403: TN | D403: TN23AE1000 | E403: FORD | F403: Fiesta | I403: 70000 | J403: EXCHANGE ROTN | K403: Captive | L403: Vadivel Madesh | M403: 4237.29 | N403: 5000 | O403: =IF(AND(ISNUMBER(M403), ISNUMBER(I403), I403>0), M403/I403, "")
A404: FY26 | B404: Jan | C404: TN | D404: TN01BC5077 | E404: HYUNDAI | F404: Grand I10 | G404: 2017 | H404: 40183 | I404: 390000 | J404: EXCHANGE CHENNAI | K404: Captive | L404: Nirmal Cars | M404: 8474.58 | N404: 10000 | O404: =IF(AND(ISNUMBER(M404), ISNUMBER(I404), I404>0), M404/I404, "")
A405: FY26 | B405: Jan | C405: TN | D405: TN09AL4114 | E405: HONDA | F405: City | G405: 2005 | H405: 79983 | I405: 120000 | J405: EXCHANGE CHENNAI | K405: Captive | L405: Thiya Cars | M405: 4237.29 | N405: 5000 | O405: =IF(AND(ISNUMBER(M405), ISNUMBER(I405), I405>0), M405/I405, "")
A406: FY26 | B406: Jan | C406: TN | D406: TN01BD3441 | E406: HONDA | F406: Jazz | G406: 2017 | H406: 108064 | I406: 380000 | J406: EXCHANGE CHENNAI | K406: Captive | L406: Thiya Cars | M406: 4237.29 | N406: 5000 | O406: =IF(AND(ISNUMBER(M406), ISNUMBER(I406), I406>0), M406/I406, "")
A407: FY26 | B407: Jan | C407: TN | D407: TN25BE0099 | E407: MARUTI SUZUKI | F407: Ciaz | G407: 2017 | H407: 90681 | I407: 488000 | J407: EXCHANGE CHENNAI | K407: Captive | L407: Thiya Cars | M407: 8474.58 | N407: 10000 | O407: =IF(AND(ISNUMBER(M407), ISNUMBER(I407), I407>0), M407/I407, "")
A408: FY26 | B408: Jan | C408: TN | D408: TN09CH0258 | E408: VOLKSWAGEN | F408: Ameo | G408: 2016 | H408: 55381 | I408: 440000 | J408: EXCHANGE CHENNAI | K408: Captive | L408: Kirthi Cars | M408: 4237.29 | N408: 5000 | O408: =IF(AND(ISNUMBER(M408), ISNUMBER(I408), I408>0), M408/I408, "")
A409: FY26 | B409: Jan | C409: TN | D409: KL09X3376 | E409: MARUTI SUZUKI | F409: Alto | G409: 2009 | H409: 126811 | I409: 120000 | J409: EXCHANGE ROTN | K409: Captive | L409: S.R.CARS | M409: 4237.29 | N409: 5000 | O409: =IF(AND(ISNUMBER(M409), ISNUMBER(I409), I409>0), M409/I409, "")
A410: FY26 | B410: Jan | C410: TN | D410: TN38BD2741 | E410: MAHINDRA | F410: Logan | G410: 2010 | H410: 342085 | I410: 70000 | J410: EXCHANGE ROTN | K410: Captive | L410: S.R.CARS | M410: 4237.29 | N410: 5000 | O410: =IF(AND(ISNUMBER(M410), ISNUMBER(I410), I410>0), M410/I410, "")
A411: FY26 | B411: Jan | C411: TN | D411: TN75X9000 | E411: VOLKSWAGEN | F411: Polo | G411: 2016 | H411: 73917 | I411: 210000 | J411: JAIKRISHNAA AUTOSALES PRIVATE LIMITED | K411: Non-Captive | L411: S.R.CARS | M411: 4237.29 | N411: 5000 | O411: =IF(AND(ISNUMBER(M411), ISNUMBER(I411), I411>0), M411/I411, "")
A412: FY26 | B412: Jan | C412: TN | D412: TN66P3373 | E412: MARUTI SUZUKI | F412: Wagon R | G412: 2015 | H412: 45555 | I412: 190000 | J412: JAIKRISHNAA AUTOSALES PRIVATE LIMITED | K412: Non-Captive | L412: PURUSOTHAMAN J CARS | M412: 4237.29 | N412: 5000 | O412: =IF(AND(ISNUMBER(M412), ISNUMBER(I412), I412>0), M412/I412, "")
A413: FY26 | B413: Jan | C413: TN | D413: TN69BQ6541 | E413: MARUTI SUZUKI | F413: Wagon R | G413: 2022 | H413: 19411 | I413: 230000 | J413: JAIKRISHNAA AUTOSALES PRIVATE LIMITED | K413: Non-Captive | L413: PURUSOTHAMAN J CARS | M413: 4237.29 | N413: 5000 | O413: =IF(AND(ISNUMBER(M413), ISNUMBER(I413), I413>0), M413/I413, "")
A414: FY26 | B414: Jan | C414: TN | D414: TN39BF0375 | E414: MARUTI SUZUKI | F414: Alto K10 | G414: 2012 | H414: 39815 | I414: 170000 | J414: JAIKRISHNAA AUTOSALES PRIVATE LIMITED | K414: Non-Captive | L414: CAP CARS | M414: 4237.29 | N414: 5000 | O414: =IF(AND(ISNUMBER(M414), ISNUMBER(I414), I414>0), M414/I414, "")
A415: FY26 | B415: Jan | C415: TN | D415: TN39AY3701 | E415: HONDA | F415: City | G415: 2010 | H415: 106381 | I415: 240000 | J415: JAIKRISHNAA AUTOSALES PRIVATE LIMITED | K415: Non-Captive | L415: CAP CARS | M415: 4237.29 | N415: 5000 | O415: =IF(AND(ISNUMBER(M415), ISNUMBER(I415), I415>0), M415/I415, "")
... A496: FY26 | B496: Jan | C496: TN | D496: AP26BQ5479 | E496: MARUTI SUZUKI | F496: Baleno | G496: 2017 | H496: 348852 | I496: 176100 | J496: Sundharam Finance | K496: Non-Captive | L496: Essar Preowned Cars | M496: 8389.83 | N496: 9900 | O496: =IF(AND(ISNUMBER(M496), ISNUMBER(I496), I496>0), M496/I496, "")
A497: FY26 | B497: Jan | C497: TN | D497: TN06S5829 | E497: MARUTI SUZUKI | F497: Alto | I497: 168000 | J497: Khivraj Motor | K497: Non-Captive | L497: AAA Cars | M497: 5084.75 | N497: 6000 | O497: =IF(AND(ISNUMBER(M497), ISNUMBER(I497), I497>0), M497/I497, "")
A498: FY26 | B498: Jan | C498: TN | D498: TN02BT9437 | E498: HONDA | F498: City | G498: 2021 | I498: 530000 | J498: Nirmal | K498: Non-Captive | L498: Bhagavan cars | M498: 4237.29 | N498: 5000 | O498: =IF(AND(ISNUMBER(M498), ISNUMBER(I498), I498>0), M498/I498, "")
A499: FY26 | B499: Jan | C499: TN | D499: TN12AL4860 | E499: TATA | F499: Tiago | G499: 2020 | H499: 24758 | I499: 350000 | J499: PRODUCTIVITY ELEMENTS PRIVATE LIMITED | K499: Non-Captive | L499: Bhagavan cars | M499: 2966.1 | N499: 3500 | O499: =IF(AND(ISNUMBER(M499), ISNUMBER(I499), I499>0), M499/I499, "")
A500: FY26 | B500: Jan | C500: TN | D500: TN13Q0166 | E500: HYUNDAI | F500: Santro | G500: 2018 | H500: 45856 | I500: 320000 | J500: PRODUCTIVITY ELEMENTS PRIVATE LIMITED | K500: Non-Captive | L500: Bhagavan cars | M500: 2966.1 | N500: 3500 | O500: =IF(AND(ISNUMBER(M500), ISNUMBER(I500), I500>0), M500/I500, "")
A501: FY26 | B501: Jan | C501: TN | D501: TN03R2391 | E501: FORD | F501: Figo | G501: 2015 | H501: 108256 | I501: 230000 | J501: PRODUCTIVITY ELEMENTS PRIVATE LIMITED | K501: Non-Captive | L501: Bhagavan cars | M501: 2966.1 | N501: 3500 | O501: =IF(AND(ISNUMBER(M501), ISNUMBER(I501), I501>0), M501/I501, "")
A502: FY26 | B502: Jan | C502: TN | D502: TN10AY7959 | E502: HYUNDAI | F502: Grand I10 | G502: 2016 | H502: 80290 | I502: 300000 | J502: Castel Traders Honda | K502: Non-Captive | L502: Bhagavan cars | M502: 3813.56 | N502: 4500 | O502: =IF(AND(ISNUMBER(M502), ISNUMBER(I502), I502>0), M502/I502, "")
A503: FY26 | B503: Feb | C503: TN | D503: TN01AQ9263 | E503: HYUNDAI | F503: I20 | G503: 2011 | H503: 9999 | I503: 180000 | J503: Khivraj Motor | K503: Non-Captive | L503: SRIDHAR cars | M503: 2966.1 | N503: 3500 | O503: =IF(AND(ISNUMBER(M503), ISNUMBER(I503), I503>0), M503/I503, "")
A504: FY26 | B504: Feb | C504: TN | D504: TN05AS8230 | E504: FORD | F504: Fiesta | G504: 2013 | H504: 25789 | I504: 250000 | J504: Khivraj Motor | K504: Non-Captive | L504: Hasini Cars | M504: 2966.1 | N504: 3500 | O504: =IF(AND(ISNUMBER(M504), ISNUMBER(I504), I504>0), M504/I504, "")
A505: FY26 | B505: Feb | C505: TN | D505: TN59AV5922 | E505: MARUTI SUZUKI | F505: Zen | G505: 2010 | H505: 33574 | I505: 65000 | J505: Khivraj Motor | K505: Non-Captive | L505: Trust On wheels | M505: 2966.1 | N505: 3500 | O505: =IF(AND(ISNUMBER(M505), ISNUMBER(I505), I505>0), M505/I505, "")
A506: FY26 | B506: Feb | C506: TN | D506: TN22CA8456 | E506: HYUNDAI | F506: I20 | G506: 2011 | H506: 136983 | I506: 124000 | J506: Khivraj Motor | K506: Non-Captive | L506: Hema Cars | M506: 5084.75 | N506: 6000 | O506: =IF(AND(ISNUMBER(M506), ISNUMBER(I506), I506>0), M506/I506, "")
A507: FY26 | B507: Feb | C507: TN | D507: TN14D8228 | E507: MARUTI SUZUKI | F507: Celerio | G507: 2015 | H507: 65129 | I507: 98000 | J507: Khivraj Motor | K507: Non-Captive | L507: Hema Cars | M507: 2542.37 | N507: 3000 | O507: =IF(AND(ISNUMBER(M507), ISNUMBER(I507), I507>0), M507/I507, "")
A508: FY26 | B508: Feb | C508: TN | D508: TN07BT5801 | E508: MARUTI SUZUKI | F508: Alto | G508: 2012 | H508: 142670 | I508: 105000 | J508: Khivraj Motor | K508: Non-Captive | L508: Hema Cars | M508: 2542.37 | N508: 3000 | O508: =IF(AND(ISNUMBER(M508), ISNUMBER(I508), I508>0), M508/I508, "")
A509: FY26 | B509: Feb | C509: TN | D509: TN06D1174 | E509: MARUTI SUZUKI | F509: Swift Dzire | G509: 2011 | H509: 239670 | I509: 107000 | J509: Khivraj Motor | K509: Non-Captive | L509: Nirmal Cars | M509: 2542.37 | N509: 3000 | O509: =IF(AND(ISNUMBER(M509), ISNUMBER(I509), I509>0), M509/I509, "")
A510: FY26 | B510: Feb | C510: TN | D510: TN04AH8741 | E510: HONDA | F510: City | G510: 2011 | I510: 170000 | J510: EXCHANGE CHENNAI | K510: Captive | L510: Nirmal Cars | M510: 4237.29 | N510: 5000 | O510: =IF(AND(ISNUMBER(M510), ISNUMBER(I510), I510>0), M510/I510, "")
A511: FY26 | B511: Feb | C511: TN | D511: TN06T4217 | E511: TATA | F511: Tiago | G511: 2017 | H511: 166868 | I511: 185000 | J511: EXCHANGE CHENNAI | K511: Captive | L511: Santhosh Cars | M511: 4237.29 | N511: 5000 | O511: =IF(AND(ISNUMBER(M511), ISNUMBER(I511), I511>0), M511/I511, "")
A512: FY26 | B512: Feb | C512: TN | D512: TN07CE9144 | E512: HONDA | F512: Amaze | G512: 2016 | I512: 325000 | J512: EXCHANGE CHENNAI | K512: Captive | L512: Nirmal Cars | M512: 8474.58 | N512: 10000 | O512: =IF(AND(ISNUMBER(M512), ISNUMBER(I512), I512>0), M512/I512, "")
A513: FY26 | B513: Feb | C513: TN | D513: TN37CC2200 | E513: HYUNDAI | F513: I20 | G513: 2013 | H513: 68899 | I513: 205000 | J513: JAIKRISHNAA AUTOSALES PRIVATE LIMITED | K513: Non-Captive | L513: Dhidugal Value Cars | M513: 4237.29 | N513: 5000 | O513: =IF(AND(ISNUMBER(M513), ISNUMBER(I513), I513>0), M513/I513, "")
A514: FY26 | B514: Feb | C514: TN | D514: TN66M1397 | E514: NISSAN | F514: Micra | G514: 2014 | H514: 102000 | I514: 180000 | J514: JAIKRISHNAA AUTOSALES PRIVATE LIMITED | K514: Non-Captive | L514: Dhidugal Value Cars | M514: 4237.29 | N514: 5000 | O514: =IF(AND(ISNUMBER(M514), ISNUMBER(I514), I514>0), M514/I514, "")
A515: FY26 | B515: Feb | C515: TN | D515: TN37BP5128 | E515: MARUTI SUZUKI | F515: Swift | G515: 2011 | H515: 152355 | I515: 195000 | J515: JAIKRISHNAA AUTOSALES PRIVATE LIMITED | K515: Non-Captive | L515: Dhidugal Value Cars | M515: 4237.29 | N515: 5000 | O515: =IF(AND(ISNUMBER(M515), ISNUMBER(I515), I515>0), M515/I515, "")
A516: FY26 | B516: Feb | C516: TN | D516: TN66M7261 | E516: MARUTI SUZUKI | F516: Alto K10 | G516: 2014 | H516: 159877 | I516: 210000 | J516: JAIKRISHNAA AUTOSALES PRIVATE LIMITED | K516: Non-Captive | L516: Dhidugal Value Cars | M516: 4237.29 | N516: 5000 | O516: =IF(AND(ISNUMBER(M516), ISNUMBER(I516), I516>0), M516/I516, "")
A517: FY26 | B517: Feb | C517: TN | D517: TN38BH6333 | E517: FORD | F517: Figo | G517: 2011 | H517: 111803 | I517: 130000 | J517: JAIKRISHNAA AUTOSALES PRIVATE LIMITED | K517: Non-Captive | L517: Dhidugal Value Cars | M517: 4237.29 | N517: 5000 | O517: =IF(AND(ISNUMBER(M517), ISNUMBER(I517), I517>0), M517/I517, "")
A518: FY26 | B518: Feb | C518: TN | D518: TN07BH7797 | E518: HYUNDAI | F518: I10 | G518: 2010 | H518: 72444 | I518: 190000 | J518: JAIKRISHNAA AUTOSALES PRIVATE LIMITED | K518: Non-Captive | L518: Dhidugal Value Cars | M518: 4237.29 | N518: 5000 | O518: =IF(AND(ISNUMBER(M518), ISNUMBER(I518), I518>0), M518/I518, "")
...

Sheet Conversion Data (Standard)
A1: TVS Certified - Monthly Conversion Report (Standard)
A2: January to September 2026 - Standard 13-Column Manager Reporting Template
A3: FY | B3: Month | C3: State | D3: Vehicle Number | E3: Make | F3: Model | G3: Year | H3: Odometer | I3: Final Bid Value | J3: Seller Name | K3: Seller Segment | L3: Buyer Name | M3: Total Income
A4: FY26 | B4: Jan | C4: AP/TS | D4: AP31AS1112 | E4: HYUNDAI | F4: Getz | G4: 2007 | H4: 77543 | I4: 55000 | J4: Exchange VIZAG | K4: Captive | L4: Gadi Sri Bharathi | M4: 4237.29
A5: FY26 | B5: Jan | C5: AP/TS | D5: AP31CS7594 | E5: HONDA | F5: Mobilio | G5: 2014 | H5: 98056 | I5: 265000 | J5: Exchange VIZAG | K5: Captive | L5: Siva Reddy Gudla | M5: 12711.86
A6: FY26 | B6: Jan | C6: AP/TS | D6: TS09EY7211 | E6: NISSAN | F6: Micra | G6: 2017 | H6: 113473 | I6: 190000 | J6: Exchange HYDERABAD | K6: Captive | L6: Viswanadhapalli Aravind | M6: 8474.58
A7: FY26 | B7: Jan | C7: AP/TS | D7: AP31CE7777 | E7: RENAULT | F7: Scala | G7: 2012 | H7: 255641 | I7: 97000 | J7: Exchange VIZAG | K7: Captive | L7: Kaki Dinesh Kumar | M7: 5932.2
A8: FY26 | B8: Jan | C8: AP/TS | D8: AP31DF2198 | E8: HONDA | F8: Jazz | G8: 2016 | H8: 41567 | I8: 327500 | J8: Exchange VIZAG | K8: Captive | L8: Chukka Satish | M8: 10593.22
A9: FY26 | B9: Jan | C9: AP/TS | D9: AP31BM4257 | E9: CHEVROLET | F9: Spark | G9: 2015 | H9: 141008 | I9: 50000 | J9: Kesireddi Saikiran | K9: Non-Captive | L9: Siva Reddy Gudla | M9: 4237.29
A10: FY26 | B10: Jan | C10: AP/TS | D10: TS08GV4028 | E10: HONDA | F10: Amaze | G10: 2019 | H10: 74555 | I10: 380000 | J10: Exchange HYDERABAD | K10: Captive | L10: Ganothula Brahma Reddy | M10: 8474.58
A11: FY26 | B11: Jan | C11: AP/TS | D11: TS09EB2697 | E11: HONDA | F11: City | G11: 2014 | H11: 158986 | I11: 265000 | J11: Exchange HYDERABAD | K11: Captive | L11: Uppari Sandeep Kumar | M11: 8474.58
A12: FY26 | B12: Jan | C12: AP/TS | D12: TS11EC4656 | E12: HONDA | F12: Amaze | G12: 2015 | H12: 178445 | I12: 215000 | J12: Exchange HYDERABAD | K12: Captive | L12: Puneet Gupta | M12: 8474.58
A13: FY26 | B13: Jan | C13: AP/TS | D13: AP39JV0286 | E13: TATA | F13: Tiago | G13: 2021 | H13: 58833 | I13: 335000 | J13: Exchange VIJAYAWADA | K13: Captive | L13: Naga Suresh Polukonda | M13: 8474.58
A14: FY26 | B14: Jan | C14: AP/TS | D14: AP31DD1661 | E14: HONDA | F14: Jazz | G14: 2015 | H14: 132923 | I14: 240000 | J14: Exchange VIZAG | K14: Captive | L14: Raju Avaala | M14: 8474.58
A15: FY26 | B15: Jan | C15: AP/TS | D15: AP31EP0888 | E15: HONDA | F15: Amaze | G15: 2018 | H15: 85923 | I15: 400000 | J15: Exchange VIZAG | K15: Captive | L15: Kaki Dinesh Kumar | M15: 12711.86
... A318: FY26 | B318: Jan | C318: TN | D318: TN06B2738 | E318: HYUNDAI | F318: I10 | G318: 2010 | H318: 124567 | I318: 180000 | J318: Nirmal | K318: Non-Captive | L318: Ragupathy Cars | M318: 4237.29
A319: FY26 | B319: Jan | C319: TN | D319: KL24L2932 | E319: HONDA | F319: Jazz | I319: 350000 | J319: Nippon Motor Corporation Pvt Ltd | K319: Non-Captive | L319: Shamnad AH | M319: 5932.2
A320: FY26 | B320: Jan | C320: TN | D320: KL29M9531 | E320: HYUNDAI | F320: Verna | I320: 360000 | J320: Nippon Motor Corporation Pvt Ltd | K320: Non-Captive | L320: Shamnad AH | M320: 5932.2
A321: FY26 | B321: Jan | C321: TN | D321: TN13H5670 | E321: TATA | F321: Tiago | G321: 2017 | H321: 79008 | I321: 250000 | J321: Lakshmi Tata | K321: Non-Captive | L321: Omega Car Zone | M321: 4237.29
A322: FY26 | B322: Jan | C322: TN | D322: TN10BB1885 | E322: MARUTI SUZUKI | F322: Swift Dzire | G322: 2017 | H322: 110113 | I322: 400000 | J322: Lakshmi Tata | K322: Non-Captive | L322: Thiya Cars | M322: 4237.29
A323: FY26 | B323: Jan | C323: TN | D323: TN12AM7659 | E323: RENAULT | F323: Kiger | G323: 2021 | H323: 41621 | I323: 260000 | J323: Lakshmi Tata | K323: Non-Captive | L323: Thiya Cars | M323: 4237.29
A324: FY26 | B324: Jan | C324: TN | D324: TN02BC1360 | E324: RENAULT | F324: Logdy | G324: 2015 | H324: 67756 | I324: 300000 | J324: Lakshmi Tata | K324: Non-Captive | L324: Thiya Cars | M324: 4237.29
A325: FY26 | B325: Jan | C325: TN | D325: TN13E0081 | E325: MARUTI SUZUKI | F325: Alto | G325: 2016 | H325: 44733 | I325: 150000 | J325: Lakshmi Tata | K325: Non-Captive | L325: Thiya Cars | M325: 4237.29
A326: FY26 | B326: Jan | C326: TN | D326: TN12E7768 | E326: HYUNDAI | F326: Grand I10 | G326: 2014 | H326: 77642 | I326: 200000 | J326: Lakshmi Tata | K326: Non-Captive | L326: Thiya Cars | M326: 4237.29
A327: FY26 | B327: Jan | C327: TN | D327: TN01U6000 | E327: MARUTI SUZUKI | F327: Alto | G327: 1998 | H327: 73444 | I327: 25000 | J327: Lakshmi Tata | K327: Non-Captive | L327: Thiya Cars | M327: 4237.29
A328: FY26 | B328: Jan | C328: TN | D328: TN22CD7366 | E328: MARUTI SUZUKI | F328: Swift | G328: 2012 | H328: 55256 | I328: 160000 | J328: Lakshmi Tata | K328: Non-Captive | L328: Thiya Cars | M328: 4237.29
A329: FY26 | B329: Jan | C329: TN | D329: TN07AL9019 | E329: HONDA | F329: City | G329: 2007 | H329: 94292 | I329: 100000 | J329: Lakshmi Tata | K329: Non-Captive | L329: Thiya Cars | M329: 4237.29
A330: FY26 | B330: Jan | C330: TN | D330: TN18P1035 | E330: VOLKSWAGEN | F330: Polo | G330: 2012 | H330: 131005 | I330: 200000 | J330: Lakshmi Tata | K330: Non-Captive | L330: Thiya Cars | M330: 4237.29
A331: FY26 | B331: Jan | C331: TN | D331: TN14W0344 | E331: TATA | F331: Tiago | G331: 2019 | H331: 72435 | I331: 270000 | J331: Lakshmi Tata | K331: Non-Captive | L331: Thiya Cars | M331: 4237.29
A332: FY26 | B332: Jan | C332: TN | D332: TN03AB1023 | E332: TATA | F332: Tiago | G332: 2019 | H332: 116457 | I332: 260000 | J332: Lakshmi Tata | K332: Non-Captive | L332: Thiya Cars | M332: 4237.29
... A334: FY26 | B334: Jan | C334: TN | D334: TN09BM0228 | E334: MARUTI SUZUKI | F334: Swift | G334: 2011 | H334: 174000 | I334: 185000 | J334: Khivraj Motor | K334: Non-Captive | L334: Balakrishnan | M334: 5084.75
A335: FY26 | B335: Jan | C335: TN | D335: TN30BL266 | E335: MARUTI SUZUKI | F335: S-Cross | I335: 485000 | J335: Khivraj Motor | K335: Non-Captive | L335: Balakrishnan | M335: 5084.75
A336: FY26 | B336: Jan | C336: TN | D336: TN09BA4646 | E336: MARUTI SUZUKI | F336: Zen | G336: 2009 | H336: 82508 | I336: 90000 | J336: Khivraj Motor | K336: Non-Captive | L336: AAA Cars | M336: 5084.75
A337: FY26 | B337: Jan | C337: TN | D337: TN01BB5113 | E337: HYUNDAI | F337: Creta | G337: 2016 | H337: 67577 | I337: 465000 | J337: Khivraj Motor | K337: Non-Captive | L337: Aasim Motor | M337: 5084.75
A338: FY26 | B338: Jan | C338: TN | D338: TN01AQ1698 | E338: MARUTI SUZUKI | F338: Swift Dzire | G338: 2011 | H338: 65103 | I338: 173000 | J338: Khivraj Motor | K338: Non-Captive | L338: Surendhar Cars | M338: 5084.75
A339: FY26 | B339: Jan | C339: TN | D339: TN09CT3233 | E339: HYUNDAI | F339: Creta | G339: 2019 | H339: 44563 | I339: 530000 | J339: Harsha | K339: Non-Captive | L339: Pine Autos | M339: 5508.47
A340: FY26 | B340: Jan | C340: TN | D340: KL04AG5541 | E340: MARUTI SUZUKI | F340: Ritz | I340: 210000 | J340: Nippon Motor Corporation Pvt Ltd | K340: Non-Captive | L340: Shamnad AH | M340: 5932.2
A341: FY26 | B341: Jan | C341: TN | D341: TN01BP4170 | E341: HYUNDAI | F341: Aura | G341: 2022 | H341: 1974 | I341: 620000 | J341: Avis India | K341: Non-Captive | L341: Nirmal Cars | M341: 12711.86
A342: FY26 | B342: Jan | C342: TN | D342: TN38CB0766 | E342: HONDA | F342: Amaze | G342: 2015 | H342: 65500 | I342: 190000 | J342: Sai Cars CBE | K342: Non-Captive | L342: KSM AUTO CONSULTING | M342: 4237.29
A343: FY26 | B343: Jan | C343: TN | D343: TN01AC1548 | E343: TATA | F343: Indica | G343: 2006 | H343: 160671 | I343: 60000 | J343: Sai Cars CBE | K343: Non-Captive | L343: KSM AUTO CONSULTING | M343: 4237.29
A344: FY26 | B344: Jan | C344: TN | D344: TN05AS2905 | E344: TOYOTA | F344: Etios | G344: 2013 | H344: 83523 | I344: 180000 | J344: Sai Cars CBE | K344: Non-Captive | L344: YUGA DHEERAN CARS | M344: 4237.29
A345: FY26 | B345: Jan | C345: TN | D345: TN38BZ6252 | E345: MARUTI SUZUKI | F345: Alto K10 | G345: 2014 | H345: 102682 | I345: 170000 | J345: EXCHANGE ROTN | K345: Captive | L345: UZHAVAN ENTERPRISE | M345: 4237.29
A346: FY26 | B346: Jan | C346: TN | D346: TN07BU5814 | E346: MARUTI SUZUKI | F346: Wagon R | G346: 2013 | H346: 22988 | I346: 205000 | J346: Sai Cars CBE | K346: Non-Captive | L346: SIVASHANKAR CARS | M346: 4237.29
A347: FY26 | B347: Jan | C347: TN | D347: TN38CT0789 | E347: MARUTI SUZUKI | F347: Celerio | G347: 2019 | H347: 46670 | I347: 210000 | J347: EXCHANGE ROTN | K347: Captive | L347: 9 MILES CARZ | M347: 4237.29
A348: FY26 | B348: Jan | C348: TN | D348: KA53MA6163 | E348: HYUNDAI | F348: I10 | G348: 2013 | H348: 130298 | I348: 150000 | J348: DINDIGUL VALUE CAR | K348: Non-Captive | L348: 9 MILES CARZ | M348: 4237.29
A349: FY26 | B349: Jan | C349: TN | D349: TN38CB2589 | E349: HYUNDAI | F349: Grand I10 | G349: 2015 | H349: 54895 | I349: 190000 | J349: Sai Cars CBE | K349: Non-Captive | L349: Dheera Cars | M349: 4237.29
A350: FY26 | B350: Jan | C350: TN | D350: TN91W8213 | E350: MARUTI SUZUKI | F350: Alto | G350: 2018 | H350: 25663 | I350: 210000 | J350: Sai Cars CBE | K350: Non-Captive | L350: Dheera Cars | M350: 4237.29
A351: FY26 | B351: Jan | C351: TN | D351: TN38BV1258 | E351: FORD | F351: Figo | G351: 2013 | H351: 11589 | I351: 130000 | J351: Sai Cars CBE | K351: Non-Captive | L351: Dheera Cars | M351: 4237.29
A352: FY26 | B352: Jan | C352: TN | D352: TN09BK9082 | E352: HYUNDAI | F352: I10 | G352: 2011 | H352: 89684 | I352: 115000 | J352: Sai Cars CBE | K352: Non-Captive | L352: Dheera Cars | M352: 4237.29
... A386: FY26 | B386: Jan | C386: TN | D386: TN06K7642 | E386: VOLKSWAGEN | F386: Polo | G386: 2013 | H386: 81914 | I386: 180000 | J386: Khivraj Motor | K386: Non-Captive | L386: Prem Cars | M386: 5084.75
A387: FY26 | B387: Jan | C387: TN | D387: TN09CE6262 | E387: MARUTI SUZUKI | F387: Brezza | I387: 473000 | J387: Khivraj Motor | K387: Non-Captive | L387: Senthil Cars | M387: 5084.75
A388: FY26 | B388: Jan | C388: TN | D388: TN30BQ9174 | E388: HONDA | F388: Amaze | G388: 2020 | H388: 36298 | I388: 485000 | J388: EXCHANGE ROTN | K388: Captive | L388: Sangeetha Enterprises | M388: 12711.86
A389: FY26 | B389: Jan | C389: TN | D389: DL3CCE6673 | E389: HONDA | F389: Jazz | G389: 2016 | H389: 81658 | I389: 250000 | J389: EXCHANGE ROTN | K389: Captive | L389: MS Cars | M389: 5932.2
A390: FY26 | B390: Jan | C390: TN | D390: TN72BA1515 | E390: HONDA | F390: City | G390: 2014 | H390: 143498 | I390: 375000 | J390: EXCHANGE ROTN | K390: Captive | L390: Value Cars | M390: 12711.86
A391: FY26 | B391: Jan | C391: TN | D391: TN30CE5088 | E391: HONDA | F391: Amaze | G391: 2023 | H391: 118492 | I391: 435000 | J391: EXCHANGE ROTN | K391: Captive | L391: Vadivel Madesh | M391: 4237.29
A392: FY26 | B392: Jan | C392: TN | D392: TN10H8377 | E392: MARUTI SUZUKI | F392: Zen | G392: 2004 | H392: 127346 | I392: 70000 | J392: EXCHANGE ROTN | K392: Captive | L392: Gugha Cars | M392: 4237.29
A393: FY26 | B393: Jan | C393: TN | D393: TN59BH8394 | E393: MARUTI SUZUKI | F393: Ciaz | G393: 2015 | H393: 110535 | I393: 370000 | J393: EXCHANGE ROTN | K393: Captive | L393: Selva Motors | M393: 12711.86
A394: FY26 | B394: Jan | C394: TN | D394: TN10AA7457 | E394: MARUTI SUZUKI | F394: Swift Dzire | G394: 2010 | H394: 209748 | I394: 170000 | J394: EXCHANGE CHENNAI | K394: Captive | L394: Nirmal Cars | M394: 4237.29
A395: FY26 | B395: Jan | C395: TN | D395: TN06Y6543 | E395: HONDA | F395: Amaze | G395: 2019 | H395: 37168 | I395: 450000 | J395: EXCHANGE CHENNAI | K395: Captive | L395: Thiya Cars | M395: 4237.29
A396: FY26 | B396: Jan | C396: TN | D396: TN49BA3864 | E396: HYUNDAI | F396: Grand I10 | G396: 2014 | H396: 79642 | I396: 250000 | J396: EXCHANGE ROTN | K396: Captive | L396: Sai cars | M396: 6779.66
A397: FY26 | B397: Jan | C397: TN | D397: TN30BV6746 | E397: HYUNDAI | F397: Eon | G397: 2017 | H397: 28450 | I397: 240000 | J397: EXCHANGE ROTN | K397: Captive | L397: SMS Cars | M397: 12711.86
A398: FY26 | B398: Jan | C398: TN | D398: TN33AT6482 | E398: MARUTI SUZUKI | F398: Alto | G398: 2011 | H398: 43110 | I398: 200000 | J398: EXCHANGE ROTN | K398: Captive | L398: YUGA DHEERAN CARS | M398: 8474.58
A399: FY26 | B399: Jan | C399: TN | D399: TN19AK4891 | E399: MARUTI SUZUKI | F399: Swift | G399: 2018 | H399: 91489 | I399: 500000 | J399: EXCHANGE ROTN | K399: Captive | L399: Gugha Cars | M399: 8474.58
... A402: FY26 | B402: Jan | C402: TN | D402: TN58AU4124 | E402: TATA | F402: Tiago | G402: 2017 | H402: 92823 | I402: 285000 | J402: EXCHANGE ROTN | K402: Captive | L402: Dheera Cars | M402: 12711.86
A403: FY26 | B403: Jan | C403: TN | D403: TN23AE1000 | E403: FORD | F403: Fiesta | I403: 70000 | J403: EXCHANGE ROTN | K403: Captive | L403: Vadivel Madesh | M403: 4237.29
A404: FY26 | B404: Jan | C404: TN | D404: TN01BC5077 | E404: HYUNDAI | F404: Grand I10 | G404: 2017 | H404: 40183 | I404: 390000 | J404: EXCHANGE CHENNAI | K404: Captive | L404: Nirmal Cars | M404: 8474.58
A405: FY26 | B405: Jan | C405: TN | D405: TN09AL4114 | E405: HONDA | F405: City | G405: 2005 | H405: 79983 | I405: 120000 | J405: EXCHANGE CHENNAI | K405: Captive | L405: Thiya Cars | M405: 4237.29
A406: FY26 | B406: Jan | C406: TN | D406: TN01BD3441 | E406: HONDA | F406: Jazz | G406: 2017 | H406: 108064 | I406: 380000 | J406: EXCHANGE CHENNAI | K406: Captive | L406: Thiya Cars | M406: 4237.29
A407: FY26 | B407: Jan | C407: TN | D407: TN25BE0099 | E407: MARUTI SUZUKI | F407: Ciaz | G407: 2017 | H407: 90681 | I407: 488000 | J407: EXCHANGE CHENNAI | K407: Captive | L407: Thiya Cars | M407: 8474.58
A408: FY26 | B408: Jan | C408: TN | D408: TN09CH0258 | E408: VOLKSWAGEN | F408: Ameo | G408: 2016 | H408: 55381 | I408: 440000 | J408: EXCHANGE CHENNAI | K408: Captive | L408: Kirthi Cars | M408: 4237.29
A409: FY26 | B409: Jan | C409: TN | D409: KL09X3376 | E409: MARUTI SUZUKI | F409: Alto | G409: 2009 | H409: 126811 | I409: 120000 | J409: EXCHANGE ROTN | K409: Captive | L409: S.R.CARS | M409: 4237.29
A410: FY26 | B410: Jan | C410: TN | D410: TN38BD2741 | E410: MAHINDRA | F410: Logan | G410: 2010 | H410: 342085 | I410: 70000 | J410: EXCHANGE ROTN | K410: Captive | L410: S.R.CARS | M410: 4237.29
A411: FY26 | B411: Jan | C411: TN | D411: TN75X9000 | E411: VOLKSWAGEN | F411: Polo | G411: 2016 | H411: 73917 | I411: 210000 | J411: JAIKRISHNAA AUTOSALES PRIVATE LIMITED | K411: Non-Captive | L411: S.R.CARS | M411: 4237.29
A412: FY26 | B412: Jan | C412: TN | D412: TN66P3373 | E412: MARUTI SUZUKI | F412: Wagon R | G412: 2015 | H412: 45555 | I412: 190000 | J412: JAIKRISHNAA AUTOSALES PRIVATE LIMITED | K412: Non-Captive | L412: PURUSOTHAMAN J CARS | M412: 4237.29
A413: FY26 | B413: Jan | C413: TN | D413: TN69BQ6541 | E413: MARUTI SUZUKI | F413: Wagon R | G413: 2022 | H413: 19411 | I413: 230000 | J413: JAIKRISHNAA AUTOSALES PRIVATE LIMITED | K413: Non-Captive | L413: PURUSOTHAMAN J CARS | M413: 4237.29
A414: FY26 | B414: Jan | C414: TN | D414: TN39BF0375 | E414: MARUTI SUZUKI | F414: Alto K10 | G414: 2012 | H414: 39815 | I414: 170000 | J414: JAIKRISHNAA AUTOSALES PRIVATE LIMITED | K414: Non-Captive | L414: CAP CARS | M414: 4237.29
A415: FY26 | B415: Jan | C415: TN | D415: TN39AY3701 | E415: HONDA | F415: City | G415: 2010 | H415: 106381 | I415: 240000 | J415: JAIKRISHNAA AUTOSALES PRIVATE LIMITED | K415: Non-Captive | L415: CAP CARS | M415: 4237.29
... A496: FY26 | B496: Jan | C496: TN | D496: AP26BQ5479 | E496: MARUTI SUZUKI | F496: Baleno | G496: 2017 | H496: 348852 | I496: 176100 | J496: Sundharam Finance | K496: Non-Captive | L496: Essar Preowned Cars | M496: 8389.83
A497: FY26 | B497: Jan | C497: TN | D497: TN06S5829 | E497: MARUTI SUZUKI | F497: Alto | I497: 168000 | J497: Khivraj Motor | K497: Non-Captive | L497: AAA Cars | M497: 5084.75
A498: FY26 | B498: Jan | C498: TN | D498: TN02BT9437 | E498: HONDA | F498: City | G498: 2021 | I498: 530000 | J498: Nirmal | K498: Non-Captive | L498: Bhagavan cars | M498: 4237.29
A499: FY26 | B499: Jan | C499: TN | D499: TN12AL4860 | E499: TATA | F499: Tiago | G499: 2020 | H499: 24758 | I499: 350000 | J499: PRODUCTIVITY ELEMENTS PRIVATE LIMITED | K499: Non-Captive | L499: Bhagavan cars | M499: 2966.1
A500: FY26 | B500: Jan | C500: TN | D500: TN13Q0166 | E500: HYUNDAI | F500: Santro | G500: 2018 | H500: 45856 | I500: 320000 | J500: PRODUCTIVITY ELEMENTS PRIVATE LIMITED | K500: Non-Captive | L500: Bhagavan cars | M500: 2966.1
A501: FY26 | B501: Jan | C501: TN | D501: TN03R2391 | E501: FORD | F501: Figo | G501: 2015 | H501: 108256 | I501: 230000 | J501: PRODUCTIVITY ELEMENTS PRIVATE LIMITED | K501: Non-Captive | L501: Bhagavan cars | M501: 2966.1
A502: FY26 | B502: Jan | C502: TN | D502: TN10AY7959 | E502: HYUNDAI | F502: Grand I10 | G502: 2016 | H502: 80290 | I502: 300000 | J502: Castel Traders Honda | K502: Non-Captive | L502: Bhagavan cars | M502: 3813.56
A503: FY26 | B503: Feb | C503: TN | D503: TN01AQ9263 | E503: HYUNDAI | F503: I20 | G503: 2011 | H503: 9999 | I503: 180000 | J503: Khivraj Motor | K503: Non-Captive | L503: SRIDHAR cars | M503: 2966.1
A504: FY26 | B504: Feb | C504: TN | D504: TN05AS8230 | E504: FORD | F504: Fiesta | G504: 2013 | H504: 25789 | I504: 250000 | J504: Khivraj Motor | K504: Non-Captive | L504: Hasini Cars | M504: 2966.1
A505: FY26 | B505: Feb | C505: TN | D505: TN59AV5922 | E505: MARUTI SUZUKI | F505: Zen | G505: 2010 | H505: 33574 | I505: 65000 | J505: Khivraj Motor | K505: Non-Captive | L505: Trust On wheels | M505: 2966.1
A506: FY26 | B506: Feb | C506: TN | D506: TN22CA8456 | E506: HYUNDAI | F506: I20 | G506: 2011 | H506: 136983 | I506: 124000 | J506: Khivraj Motor | K506: Non-Captive | L506: Hema Cars | M506: 5084.75
A507: FY26 | B507: Feb | C507: TN | D507: TN14D8228 | E507: MARUTI SUZUKI | F507: Celerio | G507: 2015 | H507: 65129 | I507: 98000 | J507: Khivraj Motor | K507: Non-Captive | L507: Hema Cars | M507: 2542.37
A508: FY26 | B508: Feb | C508: TN | D508: TN07BT5801 | E508: MARUTI SUZUKI | F508: Alto | G508: 2012 | H508: 142670 | I508: 105000 | J508: Khivraj Motor | K508: Non-Captive | L508: Hema Cars | M508: 2542.37
A509: FY26 | B509: Feb | C509: TN | D509: TN06D1174 | E509: MARUTI SUZUKI | F509: Swift Dzire | G509: 2011 | H509: 239670 | I509: 107000 | J509: Khivraj Motor | K509: Non-Captive | L509: Nirmal Cars | M509: 2542.37
A510: FY26 | B510: Feb | C510: TN | D510: TN04AH8741 | E510: HONDA | F510: City | G510: 2011 | I510: 170000 | J510: EXCHANGE CHENNAI | K510: Captive | L510: Nirmal Cars | M510: 4237.29
A511: FY26 | B511: Feb | C511: TN | D511: TN06T4217 | E511: TATA | F511: Tiago | G511: 2017 | H511: 166868 | I511: 185000 | J511: EXCHANGE CHENNAI | K511: Captive | L511: Santhosh Cars | M511: 4237.29
A512: FY26 | B512: Feb | C512: TN | D512: TN07CE9144 | E512: HONDA | F512: Amaze | G512: 2016 | I512: 325000 | J512: EXCHANGE CHENNAI | K512: Captive | L512: Nirmal Cars | M512: 8474.58
A513: FY26 | B513: Feb | C513: TN | D513: TN37CC2200 | E513: HYUNDAI | F513: I20 | G513: 2013 | H513: 68899 | I513: 205000 | J513: JAIKRISHNAA AUTOSALES PRIVATE LIMITED | K513: Non-Captive | L513: Dhidugal Value Cars | M513: 4237.29
A514: FY26 | B514: Feb | C514: TN | D514: TN66M1397 | E514: NISSAN | F514: Micra | G514: 2014 | H514: 102000 | I514: 180000 | J514: JAIKRISHNAA AUTOSALES PRIVATE LIMITED | K514: Non-Captive | L514: Dhidugal Value Cars | M514: 4237.29
A515: FY26 | B515: Feb | C515: TN | D515: TN37BP5128 | E515: MARUTI SUZUKI | F515: Swift | G515: 2011 | H515: 152355 | I515: 195000 | J515: JAIKRISHNAA AUTOSALES PRIVATE LIMITED | K515: Non-Captive | L515: Dhidugal Value Cars | M515: 4237.29
A516: FY26 | B516: Feb | C516: TN | D516: TN66M7261 | E516: MARUTI SUZUKI | F516: Alto K10 | G516: 2014 | H516: 159877 | I516: 210000 | J516: JAIKRISHNAA AUTOSALES PRIVATE LIMITED | K516: Non-Captive | L516: Dhidugal Value Cars | M516: 4237.29
A517: FY26 | B517: Feb | C517: TN | D517: TN38BH6333 | E517: FORD | F517: Figo | G517: 2011 | H517: 111803 | I517: 130000 | J517: JAIKRISHNAA AUTOSALES PRIVATE LIMITED | K517: Non-Captive | L517: Dhidugal Value Cars | M517: 4237.29
A518: FY26 | B518: Feb | C518: TN | D518: TN07BH7797 | E518: HYUNDAI | F518: I10 | G518: 2010 | H518: 72444 | I518: 190000 | J518: JAIKRISHNAA AUTOSALES PRIVATE LIMITED | K518: Non-Captive | L518: Dhidugal Value Cars | M518: 4237.29
...

Sheet _MakeList
A1: BHARATBENZ
A2: CHEVROLET
A3: CITROEN
A4: DATSUN
A5: FIAT
A6: FORD
A7: HINDUSTAN MOTORS
A8: HONDA
A9: HYUNDAI
A10: JEEP
A11: KIA
A12: MAHINDRA
... A20: VOLKSWAGEN
